{
  "count": 6,
  "dump": [
    {
      "depth": 0,
      "tag": "DIV",
      "cls": "absolute inset-0 overflow-hidden",
      "w": 888,
      "h": 555,
      "src": "",
      "anim": "none",
      "tf": ""
    },
    {
      "depth": 1,
      "tag": "DIV",
      "cls": "relative h-full w-full",
      "w": 888,
      "h": 555,
      "src": "",
      "anim": "none",
      "tf": ""
    },
    {
      "depth": 2,
      "tag": "DIV",
      "cls": "absolute left-1/2 top-1/2 h-full w-full -translate-x-1/2 -translate-y-",
      "w": 888,
      "h": 555,
      "src": "",
      "anim": "none",
      "tf": "matrix(1, 0, 0, 1, -444, -277.5)"
    },
    {
      "depth": 3,
      "tag": "PICTURE",
      "cls": "",
      "w": 888,
      "h": 555,
      "src": "",
      "anim": "none",
      "tf": ""
    },
    {
      "depth": 4,
      "tag": "SOURCE",
      "cls": "",
      "w": 0,
      "h": 0,
      "src": "",
      "anim": "none",
      "tf": ""
    },
    {
      "depth": 4,
      "tag": "IMG",
      "cls": "h-full w-full rounded-2xl object-cover",
      "w": 888,
      "h": 555,
      "src": "https://www.phygitals.com/images/claw/legend-pack-1.avif",
      "anim": "none",
      "tf": ""
    }
  ]
}