{"found":true,"text":"1 of 1 TAP TO REVEAL","els":[{"tag":"DIV","cls":"relative flex min-h-[100dvh] w-full flex-col items-center justify-cent","x":0,"y":0,"w":1440,"h":1000,"fontSize":"16px","fontFamily":"ui-sans-serif","fontWeight":"400","color":"rgb(255, 255, 255)","bg":"rgb(0, 0, 0)","radius":"0px","border":"0px solid rgb(51, 51, 51)","shadow":"none","transform":"none","letterSpacing":"normal","textTransform":"none","text":"1 of 1 TAP TO REVEAL"},{"tag":"DIV","cls":"pointer-events-none absolute inset-0","x":0,"y":0,"w":1440,"h":1000,"fontSize":"16px","fontFamily":"ui-sans-serif","fontWeight":"400","color":"rgb(255, 255, 255)","bg":"rgba(0, 0, 0, 0)","radius":"0px","border":"0px solid rgb(51, 51, 51)","shadow":"none","transform":"none","letterSpacing":"normal","textTransform":"none","text":""},{"tag":"DIV","cls":"animate-summary-fade-in absolute left-0 right-0 top-4 z-10 flex flex-c","x":0,"y":16,"w":1440,"h":28,"fontSize":"16px","fontFamily":"ui-sans-serif","fontWeight":"400","color":"rgb(255, 255, 255)","bg":"rgba(0, 0, 0, 0)","radius":"0px","border":"0px solid rgb(51, 51, 51)","shadow":"none","transform":"none","letterSpacing":"normal","textTransform":"none","text":"1 of 1"},{"tag":"DIV","cls":"mt-1.5 text-[11px] font-medium text-white/40","x":707,"y":27,"w":25,"h":17,"fontSize":"11px","fontFamily":"ui-sans-serif","fontWeight":"500","color":"rgba(255, 255, 255, 0.4)","bg":"rgba(0, 0, 0, 0)","radius":"0px","border":"0px solid rgb(51, 51, 51)","shadow":"none","transform":"none","letterSpacing":"normal","textTransform":"none","text":"1 of 1"},{"tag":"DIV","cls":"relative z-[5] flex flex-col items-center justify-center animate-swipe","x":550,"y":202,"w":340,"h":595,"fontSize":"16px","fontFamily":"ui-sans-serif","fontWeight":"400","color":"rgb(255, 255, 255)","bg":"rgba(0, 0, 0, 0)","radius":"0px","border":"0px solid rgb(51, 51, 51)","shadow":"none","transform":"matrix(1, 0, 0, 1, 0, 0)","letterSpacing":"normal","textTransform":"none","text":"TAP TO REVEAL"},{"tag":"BUTTON","cls":"cursor-pointer select-none bg-transparent p-0 focus:outline-none","x":550,"y":202,"w":340,"h":595,"fontSize":"16px","fontFamily":"ui-sans-serif","fontWeight":"400","color":"rgb(255, 255, 255)","bg":"rgba(0, 0, 0, 0)","radius":"0px","border":"0px solid rgb(51, 51, 51)","shadow":"none","transform":"none","letterSpacing":"normal","textTransform":"none","text":"TAP TO REVEAL"},{"tag":"DIV","cls":"swipe-cardback-tilt","x":547,"y":195,"w":347,"h":575,"fontSize":"16px","fontFamily":"ui-sans-serif","fontWeight":"400","color":"rgb(255, 255, 255)","bg":"rgba(0, 0, 0, 0)","radius":"0px","border":"0px solid rgb(51, 51, 51)","shadow":"none","transform":"matrix3d(1.01938, 8.81204e-06, 0.107142, 0, 0, 1.025, -8.43028e-05, 0, -0.104528","letterSpacing":"normal","textTransform":"none","text":""},{"tag":"DIV","cls":"relative","x":547,"y":195,"w":347,"h":575,"fontSize":"16px","fontFamily":"ui-sans-serif","fontWeight":"400","color":"rgb(255, 255, 255)","bg":"rgba(0, 0, 0, 0)","radius":"0px","border":"0px solid rgb(51, 51, 51)","shadow":"none","transform":"none","letterSpacing":"normal","textTransform":"none","text":""},{"tag":"IMG","cls":"h-full w-full select-none object-contain","x":547,"y":195,"w":347,"h":575,"fontSize":"16px","fontFamily":"ui-sans-serif","fontWeight":"400","color":"rgb(255, 255, 255)","bg":"rgba(0, 0, 0, 0)","radius":"0px","border":"0px solid rgb(51, 51, 51)","shadow":"none","transform":"none","letterSpacing":"normal","textTransform":"none","text":""},{"tag":"DIV","cls":"pointer-events-none absolute inset-0 overflow-hidden rounded-[7%]","x":547,"y":195,"w":347,"h":575,"fontSize":"16px","fontFamily":"ui-sans-serif","fontWeight":"400","color":"rgb(255, 255, 255)","bg":"rgba(0, 0, 0, 0)","radius":"7%","border":"0px solid rgb(51, 51, 51)","shadow":"none","transform":"none","letterSpacing":"normal","textTransform":"none","text":""},{"tag":"DIV","cls":"revealv4-celestial-shimmer absolute inset-0","x":547,"y":195,"w":347,"h":575,"fontSize":"16px","fontFamily":"ui-sans-serif","fontWeight":"400","color":"rgb(255, 255, 255)","bg":"rgba(0, 0, 0, 0)","radius":"0px","border":"0px solid rgb(51, 51, 51)","shadow":"none","transform":"none","letterSpacing":"normal","textTransform":"none","text":""},{"tag":"DIV","cls":"revealv4-celestial-shimmer-back absolute inset-0","x":547,"y":195,"w":347,"h":575,"fontSize":"16px","fontFamily":"ui-sans-serif","fontWeight":"400","color":"rgb(255, 255, 255)","bg":"rgba(0, 0, 0, 0)","radius":"0px","border":"0px solid rgb(51, 51, 51)","shadow":"none","transform":"none","letterSpacing":"normal","textTransform":"none","text":""},{"tag":"DIV","cls":"swipe-cardback-highlight pointer-events-none absolute inset-0 overflow","x":547,"y":195,"w":347,"h":575,"fontSize":"16px","fontFamily":"ui-sans-serif","fontWeight":"400","color":"rgb(255, 255, 255)","bg":"rgba(0, 0, 0, 0)","radius":"7%","border":"0px solid rgb(51, 51, 51)","shadow":"none","transform":"matrix(1, 0, 0, 1, 0, 0)","letterSpacing":"normal","textTransform":"none","text":""},{"tag":"DIV","cls":"mt-[18px] flex items-center justify-center gap-1.5","x":550,"y":781,"w":340,"h":17,"fontSize":"16px","fontFamily":"ui-sans-serif","fontWeight":"400","color":"rgb(255, 255, 255)","bg":"rgba(0, 0, 0, 0)","radius":"0px","border":"0px solid rgb(51, 51, 51)","shadow":"none","transform":"none","letterSpacing":"normal","textTransform":"none","text":"TAP TO REVEAL"},{"tag":"DIV","cls":"text-[11px] font-bold tracking-[0.22em] text-white/55","x":670,"y":781,"w":112,"h":17,"fontSize":"11px","fontFamily":"ui-sans-serif","fontWeight":"700","color":"rgba(255, 255, 255, 0.55)","bg":"rgba(0, 0, 0, 0)","radius":"0px","border":"0px solid rgb(51, 51, 51)","shadow":"none","transform":"none","letterSpacing":"2.42px","textTransform":"none","text":"TAP TO REVEAL"}],"animations":[{"type":"CSSAnimation","name":"ping","state":"running","timing":{"duration":1000,"delay":0,"easing":"linear","iterations":null}},{"type":"CSSAnimation","name":"shimmer","state":"running","timing":{"duration":2000,"delay":0,"easing":"linear","iterations":null}},{"type":"CSSAnimation","name":"pull-card-in","state":"finished","timing":{"duration":500,"delay":0,"easing":"linear","iterations":1}},{"type":"CSSAnimation","name":"pull-card-in","state":"finished","timing":{"duration":500,"delay":60,"easing":"linear","iterations":1}},{"type":"CSSAnimation","name":"pull-card-in","state":"finished","timing":{"duration":500,"delay":120,"easing":"linear","iterations":1}},{"type":"CSSAnimation","name":"pull-card-in","state":"finished","timing":{"duration":500,"delay":180,"easing":"linear","iterations":1}},{"type":"CSSAnimation","name":"pull-card-in","state":"finished","timing":{"duration":500,"delay":240,"easing":"linear","iterations":1}},{"type":"CSSAnimation","name":"pull-card-in","state":"finished","timing":{"duration":500,"delay":300,"easing":"linear","iterations":1}},{"type":"CSSAnimation","name":"pull-card-in","state":"finished","timing":{"duration":500,"delay":360,"easing":"linear","iterations":1}},{"type":"CSSAnimation","name":"pull-card-in","state":"finished","timing":{"duration":500,"delay":420,"easing":"linear","iterations":1}},{"type":"CSSAnimation","name":"pull-card-in","state":"finished","timing":{"duration":500,"delay":480,"easing":"linear","iterations":1}},{"type":"CSSAnimation","name":"pull-card-in","state":"finished","timing":{"duration":500,"delay":540,"easing":"linear","iterations":1}},{"type":"CSSAnimation","name":"pull-card-in","state":"finished","timing":{"duration":500,"delay":600,"easing":"linear","iterations":1}},{"type":"CSSAnimation","name":"pull-card-in","state":"finished","timing":{"duration":500,"delay":660,"easing":"linear","iterations":1}},{"type":"CSSAnimation","name":"pull-card-in","state":"finished","timing":{"duration":500,"delay":720,"easing":"linear","iterations":1}},{"type":"CSSAnimation","name":"pull-card-in","state":"finished","timing":{"duration":500,"delay":780,"easing":"linear","iterations":1}},{"type":"CSSAnimation","name":"pull-card-in","state":"finished","timing":{"duration":500,"delay":840,"easing":"linear","iterations":1}},{"type":"CSSAnimation","name":"pull-card-in","state":"finished","timing":{"duration":500,"delay":900,"easing":"linear","iterations":1}},{"type":"CSSAnimation","name":"pull-card-in","state":"finished","timing":{"duration":500,"delay":960,"easing":"linear","iterations":1}},{"type":"CSSAnimation","name":"pull-card-in","state":"finished","timing":{"duration":500,"delay":1020,"easing":"linear","iterations":1}}]}